pykickstart/.env
pykickstart/__init__.py
pykickstart/__main__.py
pykickstart/cli.py
pykickstart/gemini_utils.py
pykickstart/project_utils.py
pykickstart/reqs_handler.py
pykickstart/shell_utils.py
pykickstart/venv_utils.py
pykickstart_cli-0.2.6.dist-info/METADATA
pykickstart_cli-0.2.6.dist-info/WHEEL
pykickstart_cli-0.2.6.dist-info/entry_points.txt
pykickstart_cli-0.2.6.dist-info/RECORD
